Metadata-Version: 1.0
Name: skeltest
Version: 0.1
Summary: skeltest
Home-page: UNKNOWN
Author: David Hull
Author-email: davidhullster@gmail.com
License: UNKNOWN
Platform: UNKNOWN
